{
  "status": [
    { "id": 1, "status": "Green", "noOfEmployee": 843 },
    { "id": 2, "status": "Amber", "noOfEmployee": 9 },
    { "id": 3, "status": "Red", "noOfEmployee": 2 }
  ],
  "notifications": [
    { "id": 1, "request_no":"E01", "description": "Request status update", "status": "Pending", "date": "2020-07-13T10:56:15.000Z"},
    { "id": 2, "request_no":"E02", "description": "Request status update", "status": "Pending", "date": "2020-07-13T08:06:15.000Z"},
    { "id": 3, "request_no":"E03", "description": "Positive Report for COVID-19", "status": "Actioned", "date": "2020-07-13T07:50:15.000Z"},
    { "id": 4, "request_no":"E04", "description": "Request status update", "status": "Accepted", "date": "2020-07-13T07:30:15.000Z"},
    { "id": 5, "request_no":"E05", "description": "Request status update", "status": "Accepted", "date": "2020-07-13T06:51:15.000Z"},
    { "id": 6, "request_no":"E06", "description": "Request status update", "status": "Accepted", "date": "2020-07-13T04:56:15.000Z"},
    { "id": 7, "request_no":"E07", "description": "Request status update", "status": "Accepted", "date": "2020-07-13T02:56:15.000Z"},
    { "id": 8, "request_no":"E08", "description": "Request status update", "status": "Accepted", "date": "2020-07-12T22:56:15.000Z"},
    { "id": 9, "request_no":"E09", "description": "Request status update", "status": "Accepted", "date": "2020-07-12T18:32:15.000Z"},
    { "id": 10, "request_no":"E010", "description": "Request status update", "status": "Accepted", "date": "2020-07-12T12:50:15.000Z"},
    { "id": 11, "request_no":"E011", "description": "Request status update", "status": "Accepted", "date": "2020-07-12T10:56:15.000Z"},
    { "id": 12, "request_no":"E012", "description": "Request status update", "status": "Accepted", "date": "2020-07-12T05:00:15.000Z"},
    { "id": 13, "request_no":"E013", "description": "Request status update", "status": "Denied", "date": "2020-07-12T03:56:15.000Z"},
    { "id": 14, "request_no":"E014", "description": "Positive Report for COVID-19", "status": "Actioned", "date": "2020-07-12T03:00:15.000Z"},
    { "id": 15, "request_no":"E015", "description": "Request status update", "status": "Accepted", "date": "2020-07-12T01:43:15.000Z"},
    { "id": 16, "request_no":"E016", "description": "Request status update", "status": "Accepted", "date": "2020-07-11T23:55:15.000Z"},
    { "id": 17, "request_no":"E017", "description": "Request status update", "status": "Accepted", "date": "2020-07-11T22:06:15.000Z"},
    { "id": 18, "request_no":"E018", "description": "Request status update", "status": "Accepted", "date": "2020-07-11T20:16:15.000Z"},
    { "id": 19, "request_no":"E019", "description": "Request status update", "status": "Accepted", "date": "2020-07-11T19:04:15.000Z"},
    { "id": 20, "request_no":"E020", "description": "Request status update", "status": "Accepted", "date": "2020-07-11T18:26:15.000Z"},
    { "id": 21, "request_no":"E021", "description": "Request status update", "status": "Accepted", "date": "2020-07-11T13:09:15.000Z"},
    { "id": 22, "request_no":"E022", "description": "Request status update", "status": "Accepted", "date": "2020-07-11T12:02:15.000Z"},
    { "id": 23, "request_no":"E023", "description": "Request status update", "status": "Accepted", "date": "2020-07-11T12:00:15.000Z"},
    { "id": 24, "request_no":"E024", "description": "Request status update", "status": "Accepted", "date": "2020-07-11T10:20:15.000Z"},
    { "id": 25, "request_no":"E025", "description": "Request status update", "status": "Accepted", "date": "2020-07-11T10:16:15.000Z"},
    { "id": 26, "request_no":"E026", "description": "Request status update", "status": "Accepted", "date": "2020-07-11T09:00:15.000Z"},
    { "id": 27, "request_no":"E027", "description": "Request status update", "status": "Accepted", "date": "2020-07-11T03:22:15.000Z"},
    { "id": 28, "request_no":"E028", "description": "Request status update", "status": "Accepted", "date": "2020-07-11T02:15:15.000Z"},
    { "id": 29, "request_no":"E029", "description": "Request status update", "status": "Accepted", "date": "2020-07-11T01:50:15.000Z"},
    { "id": 30, "request_no":"E030", "description": "Request status update", "status": "Accepted", "date": "2020-07-11T01:12:15.000Z"},
  ],
  "profile": {
    "name": "typicode"
  }
}
